{
  "Id": 1,
  "Image": "/images/cars/J/Jaguar/cx75.jpg",
  "Class": "A",
  "Brand": "Jaguar",
  "Model": "C-X75",
  "normalizedKey": "jaguar_c_x75",
  "status": "in progress",
  "message": "Still adding data",
  "Rarity": "Epic",
  "Stars": 5,
  "Country": "UK",
  "Epics": 12,
  "ObtainableVia": null,
  "Gold_Max_Rank": 3898,
  "Gold_Top_Speed": 369.2,
  "Gold_Acceleration": 75.54,
  "Gold_Handling": 73.17,
  "Gold_Nitro": 74.12,
  "Added": "British Season",
  "Added_With": "Unleashed",
  "Added date": "27/08/2020",
  "Total upgrade cost": null,
  "Total GL points": null,
  "BPs_1_Star": 50,
  "BPs_2_Star": 23,
  "BPs_3_Star": 27,
  "BPs_4_Star": 36,
  "BPs_5_Star": 51,
  "Garage_Lvl": 50,
  "Nitro_TS": null,
  "Unnamed: 16": "384,0",
  "Perfect_Nitro_TS": null,
  "Tags": "Europe"
}
