{
  "Id": 1,
  "Image": "/images/cars/M/MercedesBenz/slrmclaren.jpg",
  "Class": "B",
  "Brand": "Mercedes-Benz",
  "Model": "SLR McLaren",
  "Rarity": "Epic",
  "Stars": 5,
  "Country": "Germany",
  "Epics": 8,
  "ObtainableVia": null,
  "Gold_Max_Rank": 4058,
  "Gold_Top_Speed": 353.3,
  "Gold_Acceleration": 78.18,
  "Gold_Handling": 66.6,
  "Gold_Nitro": 79.54,
  "Added": "Carribean",
  "Added_With": "SE",
  "Added date": "10/04/2019",
  "BPs_1_Star": 45,
  "BPs_2_Star": 17,
  "BPs_3_Star": 23,
  "BPs_4_Star": 32,
  "BPs_5_Star": 45
}