[
  {
    "GarageLevelKey": 51,
    "xp": 1600000,
    "cars": [
      {
        "brand": "Lamborghini",
        "model": "Veneno",
        "image": "veneno.jpg"
      }
    ]
  },
  {
    "GarageLevelKey": 52,
    "xp": 1800000,
    "cars": [
      {
        "brand": "Lamborghini",
        "model": "Sesto Elemento",
        "image": "sestoelemento.jpg"
      }
    ]
  },
  {
    "GarageLevelKey": 53,
    "xp": 2000000,
    "cars": [
      {
        "brand": "Peugeot",
        "model": "Onyx",
        "image": "onyx.jpg"
      }
    ]
  },
  {
    "GarageLevelKey": 54,
    "xp": 2300000,
    "cars": [
      {
        "brand": "Pagani",
        "model": "Imola",
        "image": "imola.jpg"
      }
    ]
  },
  {
    "GarageLevelKey": 55,
    "xp": 2600000,
    "cars": [
      {
        "brand": "Ferrari",
        "model": "SF90 Stradale",
        "image": "sf90stradale.jpg"
      }
    ]
  }
]