{
   "id": 1,
   "image": "/images/cars/D/Donkervoort/d8gtoindividualseries.jpg",
  "Class": "C",
   "brand": "Donkervoort",
   "model": "D8 GTO Individual Series",
  "rarity": "Rare",
  "stars": 4,
  "Country": "The Netherlands",
  "Epics": 4,
  "ObtainableVia": null,
  "Gold_Max_Rank": 2774,
  "Gold_Top_Speed": 313,
  "Gold_Acceleration": 80.12,
  "Gold_Handling": 57.28,
  "Gold_Nitro": 62.51,
  "Added": "City of Lights",
  "Added_With": "LP",
  "Added date": "06/02/2023",
  "Total upgrade cost": null,
  "Total GL points": null,
  "BPs_1_Star": 35,
  "BPs_2_Star": 10,
  "BPs_3_Star": 21,
  "BPs_4_Star": 32,
  "Garage_Lvl": null,
  "Nitro_TS": null,
  "Perfect_Nitro_TS": null,
  "Tags": null,
  "Unnamed: 16": "325,5"
}
