[
  {
    "Id": 1,
    "Image": "/images/cars/B/BMW/z4lcie89.jpg",
    "Class": "D",
    "Brand": "BMW",
    "Model": "Z4 LCI E89",
    "Rarity": "Uncommon",
    "Stars": 3,
    "Max_Rank": 1476,
    "Epics": 0,
    "Obtainable_via": "GL01",
    "Garage_Lvl": 1,
    "Top_Speed": "266,8",
    "Acceleration": "68,86",
    "Handling": "47,43",
    "Nitro": "57,49",
    "Nitro_TS": "278,0",
    "Unnamed: 16": "277,5",
    "Perfect_Nitro_TS": null,
    "Added": "Soft Launch",
    "Added_with": null,
    "Added_date": "26/02/2018",
    "Total_upgrade_cost": null,
    "Total_GL_points": null,
    "Country": "Germany",
    "Tags": "Europe",
    "BPs_1_Star": 5,
    "BPs_2_Star": 8,
    "BPs_3_Star": 45
  },
  {
    "Id": 2,
    "Image": "/images/cars/B/BMW/i8roadster.jpg",
    "Class": "D",
    "Brand": "BMW",
    "Model": "I8 Roadster",
    "Rarity": "Rare",
    "Stars": 4,
    "Max_Rank": 2247,
    "Epics": 4,
    "Obtainable_Via": "Showroom",
    "Garage_Lvl": 23,
    "Top_Speed": "278,3",
    "Acceleration": "79,72",
    "Handling": "78,61",
    "Nitro": "66,88",
    "Nitro_TS": null,
    "Unnamed: 16": "289,4",
    "Perfect_Nitro_TS": "299,0",
    "Added": "Full Throttle",
    "Added_With": "DS",
    "Added date": "10/12/2020",
    "Total upgrade cost": null,
    "Total GL points": null,
    "Country": "Germany",
    "Tags": "Europe; Hybrid",
    "BPs_1_Star": 30,
    "BPs_2_Star": 23,
    "BPs_3_Star": 33,
    "BPs_4_Star": 42
  }
]
